qnexus/__init__.py
qnexus/config.py
qnexus/context.py
qnexus/exceptions.py
qnexus/filesystem.py
qnexus/py.typed
qnexus/cli/__init__.py
qnexus/cli/auth.py
qnexus/cli/jobs.py
qnexus/cli/projects.py
qnexus/cli/utils.py
qnexus/client/__init__.py
qnexus/client/auth.py
qnexus/client/backend_snapshots.py
qnexus/client/circuits.py
qnexus/client/credentials.py
qnexus/client/devices.py
qnexus/client/gpu_decoder_configs.py
qnexus/client/hugr.py
qnexus/client/nexus_iterator.py
qnexus/client/projects.py
qnexus/client/qir.py
qnexus/client/quotas.py
qnexus/client/results.py
qnexus/client/roles.py
qnexus/client/teams.py
qnexus/client/users.py
qnexus/client/utils.py
qnexus/client/wasm_modules.py
qnexus/client/jobs/__init__.py
qnexus/client/jobs/_compile.py
qnexus/client/jobs/_execute.py
qnexus/models/__init__.py
qnexus/models/annotations.py
qnexus/models/filters.py
qnexus/models/job_status.py
qnexus/models/language.py
qnexus/models/scope.py
qnexus/models/utils.py
qnexus/models/references/__init__.py
qnexus/models/references/base.py
qnexus/models/references/projects.py
qnexus-0.39.0.dist-info/METADATA
qnexus-0.39.0.dist-info/WHEEL
qnexus-0.39.0.dist-info/entry_points.txt
qnexus-0.39.0.dist-info/licenses/LICENSE
qnexus-0.39.0.dist-info/RECORD
