Metadata-Version: 2.4
Name: qnexus
Version: 0.39.0
Summary: Quantinuum Nexus python client.
Project-URL: homepage, https://github.com/CQCL/qnexus
Project-URL: repository, https://github.com/CQCL/qnexus
Project-URL: documentation, https://nexus.quantinuum.com/docs
Author-email: Vanya Eccles <vanya.eccles@quantinuum.com>, Aidan Keay <aidan.keay@quantinuum.com>, John Children <john.children@quantinuum.com>
License:                                  Apache License
License-File: LICENSE
Requires-Python: <4,>=3.10
Requires-Dist: click<9.0,>=8.1
Requires-Dist: colorama<1.0,>=0.4
Requires-Dist: httpx<1,>=0
Requires-Dist: hugr<1.0.0,>=0.14.0
Requires-Dist: nest-asyncio<2.0,>=1.6
Requires-Dist: pandas<3,>=2
Requires-Dist: pydantic-settings<3.0,>=2
Requires-Dist: pydantic<3.0,>=2.4
Requires-Dist: pyjwt<3.0.0,>=2.10.1
Requires-Dist: pytket<3.0,>=2.3.1
Requires-Dist: quantinuum-schemas<8.0,>=7.4.1
Requires-Dist: rich<14.0,>=13.6
Requires-Dist: websockets<16,>11
Provides-Extra: qiskit
Requires-Dist: pytket-qiskit>=0.70; extra == 'qiskit'
